mtsmultitool/__init__.py
mtsmultitool/bsdiff.c
mtsmultitool/bsdiff.cp37-win32.pyd
mtsmultitool/device.py
mtsmultitool/device_serial.py
mtsmultitool/device_types.py
mtsmultitool/lz4.c
mtsmultitool/lz4.h
mtsmultitool/ymodem.py
mtsmultitool/cli/__init__.py
mtsmultitool/cli/device_cli.py
mtsmultitool-0.2.0.dist-info/LICENSE
mtsmultitool-0.2.0.dist-info/METADATA
mtsmultitool-0.2.0.dist-info/WHEEL
mtsmultitool-0.2.0.dist-info/entry_points.txt
mtsmultitool-0.2.0.dist-info/top_level.txt
mtsmultitool-0.2.0.dist-info/RECORD
