Metadata-Version: 2.1
Name: mtsmultitool
Version: 0.2.0
Summary: Library and command line tool for working with Multitech products.
Home-page: UNKNOWN
Author: MultiTech Systems, Inc.
Author-email: 
License: Proprietary
Platform: UNKNOWN
Classifier: Development Status :: 4 - Beta
Classifier: Intended Audience :: Developers
Classifier: License :: Other/Proprietary License
Classifier: Environment :: Console
Classifier: Programming Language :: C
Classifier: Programming Language :: Python :: 3.7
Classifier: Programming Language :: Python :: 3.8
Classifier: Programming Language :: Python :: 3.9
Classifier: Topic :: Utilities
Requires-Python: >=3.7
Requires-Dist: ecdsa (>=0.15)
Requires-Dist: cbor (>=1.0.0)
Requires-Dist: pyserial (>=3.5)
Requires-Dist: xmodem (>=0.4.6)
